evaluate_depth.py
evaluate_pose.py
export_gt_depth.py
kitti_utils.py
layers.py
monodepth2.py
options.py
test_simple.py
train.py
trainer.py
utils.py
networks/__init__.py
networks/depth_decoder.py
networks/pose_cnn.py
networks/pose_decoder.py
networks/resnet_encoder.py
monodepth2-1.0.0.dist-info/LICENSE
monodepth2-1.0.0.dist-info/METADATA
monodepth2-1.0.0.dist-info/WHEEL
monodepth2-1.0.0.dist-info/top_level.txt
monodepth2-1.0.0.dist-info/RECORD
