Metadata-Version: 2.1
Name: monodepth2
Version: 1.0.0
Summary: [ICCV 2019] Monocular depth estimation from a single image
Home-page: https://github.com/AdityaNG/monodepth2
License: LICENSE
Platform: UNKNOWN
Requires-Python: >=3.6
